{"Energy":[{"symbol":"CL=F","name":"WTI Crude Oil","unit":"$/bbl","price":92.30999755859375,"change":-4.6399993896484375,"pct":-4.785971671691286},{"symbol":"BZ=F","name":"Brent Crude","unit":"$/bbl","price":95.12000274658203,"change":-3.029998779296875,"pct":-3.0871102722275197},{"symbol":"NG=F","name":"Natural Gas","unit":"$/MMBtu","price":2.578000068664551,"change":-0.029000043869018555,"pct":-1.1123913547067457},{"symbol":"HO=F","name":"Heating Oil","unit":"$/gal","price":3.4755001068115234,"change":-0.14079999923706055,"pct":-3.893482153252713},{"symbol":"RB=F","name":"RBOB Gasoline","unit":"$/gal","price":2.958199977874756,"change":-0.05579996109008789,"pct":-1.85135906503211}],"Metals":[{"symbol":"GC=F","name":"Gold","unit":"$/oz","price":4832.7001953125,"change":40.400390625,"pct":0.8430271951158628},{"symbol":"SI=F","name":"Silver","unit":"$/oz","price":79.37999725341797,"change":2.30999755859375,"pct":2.997272048450368},{"symbol":"HG=F","name":"Copper","unit":"$/lb","price":6.093999862670898,"change":0.0839996337890625,"pct":1.3976644024968812},{"symbol":"PL=F","name":"Platinum","unit":"$/oz","price":2103.10009765625,"change":8.5,"pct":0.40580538545334094},{"symbol":"PA=F","name":"Palladium","unit":"$/oz","price":1595.5,"change":5.5,"pct":0.3459119496855346}],"Grains":[{"symbol":"ZW=F","name":"Wheat","unit":"\u00a2/bu","price":589.75,"change":6.5,"pct":1.1144449207029576},{"symbol":"ZC=F","name":"Corn","unit":"\u00a2/bu","price":443.75,"change":1.25,"pct":0.2824858757062147},{"symbol":"ZS=F","name":"Soybeans","unit":"\u00a2/bu","price":1161.75,"change":-0.75,"pct":-0.06451612903225806}],"Softs":[{"symbol":"CC=F","name":"Cocoa","unit":"$/ton","price":3635.0,"change":263.0,"pct":7.7995255041518385},{"symbol":"KC=F","name":"Coffee","unit":"\u00a2/lb","price":299.6000061035156,"change":4.100006103515625,"pct":1.3874809148953047},{"symbol":"CT=F","name":"Cotton","unit":"\u00a2/lb","price":76.81999969482422,"change":0.9899978637695312,"pct":1.3055490437349522},{"symbol":"SB=F","name":"Sugar #11","unit":"\u00a2/lb","price":13.979999542236328,"change":0.15999984741210938,"pct":1.1577413237717475}],"Livestock":[{"symbol":"LE=F","name":"Live Cattle","unit":"\u00a2/lb","price":251.02499389648438,"change":2.3249969482421875,"pct":0.9348600630365309},{"symbol":"GF=F","name":"Feeder Cattle","unit":"\u00a2/lb","price":375.54998779296875,"change":1.7249755859375,"pct":0.46143931775816444},{"symbol":"HE=F","name":"Lean Hogs","unit":"\u00a2/lb","price":102.4000015258789,"change":-0.5749969482421875,"pct":-0.5583850029254348}],"Crypto":[{"symbol":"BTC-USD","name":"Bitcoin","unit":"USD","price":75492.6640625,"change":959.921875,"pct":1.2879197072679154},{"symbol":"ETH-USD","name":"Ethereum","unit":"USD","price":2368.389892578125,"change":-2.150146484375,"pct":-0.09070281239482202}]}