{"Energy":[{"symbol":"CL=F","name":"WTI Crude Oil","unit":"$/bbl","price":87.5999984741211,"change":-2.2300033569335938,"pct":-2.4824705682714017},{"symbol":"BZ=F","name":"Brent Crude","unit":"$/bbl","price":96.19000244140625,"change":-1.9899978637695312,"pct":-2.0268872047096784},{"symbol":"NG=F","name":"Natural Gas","unit":"$/MMBtu","price":2.6679999828338623,"change":0.009999990463256836,"pct":0.37622236613846216},{"symbol":"HO=F","name":"Heating Oil","unit":"$/gal","price":3.5053999423980713,"change":-0.1100001335144043,"pct":-3.0425438735612635},{"symbol":"RB=F","name":"RBOB Gasoline","unit":"$/gal","price":3.031599998474121,"change":-0.0466001033782959,"pct":-1.5138750515358834}],"Metals":[{"symbol":"GC=F","name":"Gold","unit":"$/oz","price":4813.89990234375,"change":-0.2001953125,"pct":-0.004158519940153827},{"symbol":"SI=F","name":"Silver","unit":"$/oz","price":79.73999786376953,"change":0.75,"pct":0.949487302548724},{"symbol":"HG=F","name":"Copper","unit":"$/lb","price":6.058000087738037,"change":0.014500141143798828,"pct":0.23992953209125545},{"symbol":"PL=F","name":"Platinum","unit":"$/oz","price":2100.699951171875,"change":4.099853515625,"pct":0.19554771175524363},{"symbol":"PA=F","name":"Palladium","unit":"$/oz","price":1564.0,"change":-2.0,"pct":-0.1277139208173691}],"Grains":[{"symbol":"ZW=F","name":"Wheat","unit":"\u00a2/bu","price":604.5,"change":-2.25,"pct":-0.3708281829419036},{"symbol":"ZC=F","name":"Corn","unit":"\u00a2/bu","price":458.25,"change":-0.5,"pct":-0.10899182561307902},{"symbol":"ZS=F","name":"Soybeans","unit":"\u00a2/bu","price":1159.75,"change":-3.25,"pct":-0.2794496990541703}],"Softs":[{"symbol":"CC=F","name":"Cocoa","unit":"$/ton","price":3509.0,"change":5.0,"pct":0.14269406392694062},{"symbol":"KC=F","name":"Coffee","unit":"\u00a2/lb","price":288.5,"change":-2.149993896484375,"pct":-0.7397192298755388},{"symbol":"CT=F","name":"Cotton","unit":"\u00a2/lb","price":78.58999633789062,"change":0.279998779296875,"pct":0.3575517660913883},{"symbol":"SB=F","name":"Sugar #11","unit":"\u00a2/lb","price":13.680000305175781,"change":-0.1399993896484375,"pct":-1.0130202079589712}],"Livestock":[{"symbol":"LE=F","name":"Live Cattle","unit":"\u00a2/lb","price":247.6,"change":-3.6250061035156307,"pct":-1.442932039186406},{"symbol":"GF=F","name":"Feeder Cattle","unit":"\u00a2/lb","price":368.35,"change":-3.7250122070312273,"pct":-1.001145490780376},{"symbol":"HE=F","name":"Lean Hogs","unit":"\u00a2/lb","price":101.7,"change":-0.12499694824218466,"pct":-0.1227566432491236}],"Crypto":[{"symbol":"BTC-USD","name":"Bitcoin","unit":"USD","price":75828.75,"change":645.1015625,"pct":0.8580343943221531},{"symbol":"ETH-USD","name":"Ethereum","unit":"USD","price":2361.199951171875,"change":12.58984375,"pct":0.5360550782871394}]}