{"Energy":[{"symbol":"CL=F","name":"WTI Crude Oil","unit":"$/bbl","price":97.45999908447266,"change":0.26999664306640625,"pct":0.277802897709753},{"symbol":"BZ=F","name":"Brent Crude","unit":"$/bbl","price":97.7699966430664,"change":1.149993896484375,"pct":1.1902234152286406},{"symbol":"NG=F","name":"Natural Gas","unit":"$/MMBtu","price":2.7219998836517334,"change":-0.0010001659393310547,"pct":-0.036730294569082285},{"symbol":"HO=F","name":"Heating Oil","unit":"$/gal","price":3.974600076675415,"change":0.07700014114379883,"pct":1.9755783666210558},{"symbol":"RB=F","name":"RBOB Gasoline","unit":"$/gal","price":2.9779999256134033,"change":0.04929995536804199,"pct":1.68333922453353}],"Metals":[{"symbol":"GC=F","name":"Gold","unit":"$/oz","price":4753.60009765625,"change":18.60009765625,"pct":0.3928214922122492},{"symbol":"SI=F","name":"Silver","unit":"$/oz","price":74.00499725341797,"change":-0.06500244140625,"pct":-0.08775812295675245},{"symbol":"HG=F","name":"Copper","unit":"$/lb","price":5.703000068664551,"change":-0.01699972152709961,"pct":-0.2971979396966032},{"symbol":"PL=F","name":"Platinum","unit":"$/oz","price":2031.4000244140625,"change":4.7000732421875,"pct":0.23190769997649785},{"symbol":"PA=F","name":"Palladium","unit":"$/oz","price":1575.5,"change":13.0,"pct":0.832}],"Grains":[{"symbol":"ZW=F","name":"Wheat","unit":"\u00a2/bu","price":586.25,"change":2.75,"pct":0.4712939160239932},{"symbol":"ZC=F","name":"Corn","unit":"\u00a2/bu","price":449.5,"change":1.0,"pct":0.2229654403567447},{"symbol":"ZS=F","name":"Soybeans","unit":"\u00a2/bu","price":1164.75,"change":2.75,"pct":0.23666092943201378}],"Softs":[{"symbol":"CC=F","name":"Cocoa","unit":"$/ton","price":3294.0,"change":-24.0,"pct":-0.7233273056057866},{"symbol":"KC=F","name":"Coffee","unit":"\u00a2/lb","price":275.45001220703125,"change":0.600006103515625,"pct":0.2183031072190143},{"symbol":"CT=F","name":"Cotton","unit":"\u00a2/lb","price":0.0,"change":0.0,"pct":0.0},{"symbol":"SB=F","name":"Sugar #11","unit":"\u00a2/lb","price":14.15999984741211,"change":-0.10000038146972656,"pct":-0.7012649359372967}],"Livestock":[{"symbol":"LE=F","name":"Live Cattle","unit":"\u00a2/lb","price":245.75,"change":0.1999969482421875,"pct":0.08144856271902856},{"symbol":"GF=F","name":"Feeder Cattle","unit":"\u00a2/lb","price":367.875,"change":1.45001220703125,"pct":0.3957187024184365},{"symbol":"HE=F","name":"Lean Hogs","unit":"\u00a2/lb","price":104.65,"change":-2.424996948242182,"pct":-2.2647649006372372}],"Crypto":[{"symbol":"BTC-USD","name":"Bitcoin","unit":"USD","price":71536.890625,"change":421.765625,"pct":0.5930744338844937},{"symbol":"ETH-USD","name":"Ethereum","unit":"USD","price":2192.885986328125,"change":2.707763671875,"pct":0.12363211559062175}]}