{"Energy":[{"symbol":"CL=F","name":"WTI Crude Oil","unit":"$/bbl","price":91.80999755859375,"change":0.8699951171875,"pct":0.9566693356403289},{"symbol":"BZ=F","name":"Brent Crude","unit":"$/bbl","price":95.08000183105469,"change":-0.029998779296875,"pct":-0.03154114089408385},{"symbol":"NG=F","name":"Natural Gas","unit":"$/MMBtu","price":2.611999988555908,"change":0.023000001907348633,"pct":0.8883739677852203},{"symbol":"HO=F","name":"Heating Oil","unit":"$/gal","price":3.5362000465393066,"change":0.03730010986328125,"pct":1.0660524890207796},{"symbol":"RB=F","name":"RBOB Gasoline","unit":"$/gal","price":2.9974000453948975,"change":0.03390002250671387,"pct":1.1439184155522766}],"Metals":[{"symbol":"GC=F","name":"Gold","unit":"$/oz","price":4840.2998046875,"change":-9.30029296875,"pct":-0.19177443049880985},{"symbol":"SI=F","name":"Silver","unit":"$/oz","price":80.13500213623047,"change":0.20999908447265625,"pct":0.2627451691639787},{"symbol":"HG=F","name":"Copper","unit":"$/lb","price":6.072999954223633,"change":-0.032000064849853516,"pct":-0.5241615847645803},{"symbol":"PL=F","name":"Platinum","unit":"$/oz","price":2141.10009765625,"change":12.7001953125,"pct":0.596701554934052},{"symbol":"PA=F","name":"Palladium","unit":"$/oz","price":1604.0,"change":1.5,"pct":0.093603744149766}],"Grains":[{"symbol":"ZW=F","name":"Wheat","unit":"\u00a2/bu","price":596.5,"change":-5.25,"pct":-0.8724553385957623},{"symbol":"ZC=F","name":"Corn","unit":"\u00a2/bu","price":448.0,"change":2.75,"pct":0.617630544637844},{"symbol":"ZS=F","name":"Soybeans","unit":"\u00a2/bu","price":1164.75,"change":3.75,"pct":0.32299741602067183}],"Softs":[{"symbol":"CC=F","name":"Cocoa","unit":"$/ton","price":3676.0,"change":-20.0,"pct":-0.5411255411255411},{"symbol":"KC=F","name":"Coffee","unit":"\u00a2/lb","price":301.54998779296875,"change":16.5999755859375,"pct":5.825574618286642},{"symbol":"CT=F","name":"Cotton","unit":"\u00a2/lb","price":77.5199966430664,"change":0.779998779296875,"pct":1.016417514998561},{"symbol":"SB=F","name":"Sugar #11","unit":"\u00a2/lb","price":13.760000228881836,"change":-0.3899993896484375,"pct":-2.756179506448254}],"Livestock":[{"symbol":"LE=F","name":"Live Cattle","unit":"\u00a2/lb","price":251.3000030517578,"change":-0.0500030517578125,"pct":-0.019893793731287725},{"symbol":"GF=F","name":"Feeder Cattle","unit":"\u00a2/lb","price":374.07501220703125,"change":-1.3499755859375,"pct":-0.3595859705220142},{"symbol":"HE=F","name":"Lean Hogs","unit":"\u00a2/lb","price":102.19999694824219,"change":-0.27500152587890625,"pct":-0.2683596291522315}],"Crypto":[{"symbol":"BTC-USD","name":"Bitcoin","unit":"USD","price":74177.90625,"change":-26.7421875,"pct":-0.03603842624835561},{"symbol":"ETH-USD","name":"Ethereum","unit":"USD","price":2338.0400390625,"change":14.580078125,"pct":0.627515789818777}]}